rl_test_task_1/__init__.py
rl_test_task_1/client.py
rl_test_task_1/data_exporters/__init__.py
rl_test_task_1/data_exporters/data_exporter.py
rl_test_task_1/data_exporters/generic_data_exporter.py
rl_test_task_1/data_exporters/persons_data_exporter.py
rl_test_task_1/data_exporters/exceptions/__init__.py
rl_test_task_1/data_exporters/exceptions/unsupported_data_type.py
rl_test_task_1/data_providers/__init__.py
rl_test_task_1/data_providers/data_provider.py
rl_test_task_1/data_providers/inputs_data_provider.py
rl_test_task_1/data_providers/persons_data_provider.py
rl_test_task_1/data_providers/exceptions/__init__.py
rl_test_task_1/data_providers/exceptions/too_big_input_data.py
rl_test_task_1/data_providers/models/__init__.py
rl_test_task_1/data_providers/models/input.py
rl_test_task_1/data_providers/models/person.py
rl_test_task_1/data_providers/parsers/__init__.py
rl_test_task_1/data_providers/parsers/input_data_parser.py
rl_test_task_1/data_providers/parsers/output_data_parser.py
rl_test_task_1-0.1.7.dist-info/METADATA
rl_test_task_1-0.1.7.dist-info/WHEEL
rl_test_task_1-0.1.7.dist-info/top_level.txt
rl_test_task_1-0.1.7.dist-info/RECORD
